scpi_sniffer/__init__.py
scpi_sniffer/__version__.py
scpi_sniffer/context.py
scpi_sniffer/drv_scpi_cmd.py
scpi_sniffer/drv_scpi_iface.py
scpi_sniffer/drv_scpi_node.py
SCPI_sniffer-0.0.4.dist-info/LICENSE.txt
SCPI_sniffer-0.0.4.dist-info/METADATA
SCPI_sniffer-0.0.4.dist-info/WHEEL
SCPI_sniffer-0.0.4.dist-info/top_level.txt
SCPI_sniffer-0.0.4.dist-info/RECORD
